{"from_version":"e0d1d3c0","to_version":"30c5d887","generated_at":"2026-04-28T07:14:25.457211Z","patch":[{"op":"add","path":"/cards/1551","value":{"abilities":[{"description":"Increases 42% of Crit DMG.(only take effect once to the team)","name":"Lightning Speed","tags":["Self","Crit DMG"],"unlock_level":75}],"acquisition":{"has_tower_drops":false,"sources":["gacha"]},"asset_id":"101551","bonds":[{"type":"Skill"}],"gives_special_bond":false,"has_bugs":false,"id":"1551","image_urls":{"android":"https://res.cloudinary.com/dn3j8sqcc/image/upload/v1777360455/otogi/android/101551_22dc58910f887aeec59b9fc6f8d14956.png","hd":"https://res.cloudinary.com/dn3j8sqcc/image/upload/v1777360456/otogi/cards_hd/101551_hd_3e417fcbbd717daf7727c362838b0bcf.png"},"name":"Sakuya","playable":true,"receives_special_bond":false,"skill":{"delay_lb0":"430","delay_mlb":"530","description":"Can be used as bond and in guild conquest.","name":"Full Throttle","prob_lb0":null,"prob_mlb":null,"slv_lb0":null,"slv_mlb":null,"tags":["AoE","DEF Down","Debuff"]},"stats":{"attribute_name":"Anima","base_atk":2500,"base_hp":2330,"cost":1,"crit":750,"max_atk":7500,"max_hp":7000,"max_level":60,"rarity":4,"speed":1300,"type_name":"Assist"}}},{"op":"add","path":"/cards/1550","value":{"abilities":[{"description":"Increases 15% of skill DMG dealt at the start of each wave.","name":"High Speed Travel","tags":["Wave Start","Self","Skill DMG"],"unlock_level":75},{"description":"Increases 15% of DMG dealt at the start of each wave.","name":"Cross the Fields","tags":["Wave Start","Self","DMG Boost"],"unlock_level":90}],"acquisition":{"has_tower_drops":false,"sources":["gacha"]},"asset_id":"101550","bonds":[{"type":"Attack"}],"gives_special_bond":false,"has_bugs":false,"id":"1550","image_urls":{"android":"https://res.cloudinary.com/dn3j8sqcc/image/upload/v1777360456/otogi/android/101550_9abf9498e364eaa70410b794322f664b.png","hd":"https://res.cloudinary.com/dn3j8sqcc/image/upload/v1777360457/otogi/cards_hd/101550_hd_82a5bc51e113516a629cc30aad6dbad4.png"},"name":"Loco","playable":true,"receives_special_bond":false,"skill":{"delay_lb0":null,"delay_mlb":null,"description":"Deals {value} DMG to all enemies, with a {probability} of inflicting Silence.","name":"Coal Guzzler","prob_lb0":"83.65%","prob_mlb":"100.65%","slv_lb0":"1,644","slv_mlb":"1,964","tags":["DMG","AoE","Silence","Debuff"]},"stats":{"attribute_name":"Anima","base_atk":4800,"base_hp":3200,"cost":1,"crit":2250,"max_atk":14400,"max_hp":9600,"max_level":70,"rarity":5,"speed":1300,"type_name":"Ranged"}}},{"op":"replace","path":"/cards/1616/acquisition/has_tower_drops","value":true},{"op":"add","path":"/cards/1616/acquisition/sources/0","value":"event"},{"op":"replace","path":"/cards/1607/acquisition/has_tower_drops","value":true},{"op":"add","path":"/cards/1607/acquisition/sources/0","value":"event"},{"op":"add","path":"/cards/1610/acquisition/sources/0","value":"gacha"},{"op":"add","path":"/cards/1610/acquisition/sources/1","value":"exchange"},{"op":"add","path":"/cards/1615/acquisition/sources/0","value":"gacha"},{"op":"add","path":"/cards/1615/acquisition/sources/1","value":"exchange"},{"op":"add","path":"/cards/1609/acquisition/sources/0","value":"event"},{"op":"add","path":"/cards/1602/acquisition/sources/0","value":"gacha"},{"op":"add","path":"/cards/1602/acquisition/sources/1","value":"exchange"},{"op":"add","path":"/cards/1600/acquisition/sources/0","value":"exchange"},{"op":"replace","path":"/cards/1614/acquisition/has_tower_drops","value":true},{"op":"add","path":"/cards/1614/acquisition/sources/0","value":"event"},{"op":"replace","path":"/cards/1618/acquisition/has_tower_drops","value":true},{"op":"add","path":"/cards/1618/acquisition/sources/0","value":"event"},{"op":"add","path":"/cards/1619/acquisition/sources/0","value":"gacha"},{"op":"add","path":"/cards/1619/acquisition/sources/1","value":"exchange"},{"op":"add","path":"/cards/1611/acquisition/sources/0","value":"event"},{"op":"add","path":"/cards/1601/acquisition/sources/0","value":"gacha"},{"op":"add","path":"/cards/1601/acquisition/sources/1","value":"exchange"},{"op":"replace","path":"/cards/1521/abilities/0/description","value":"Restores 12% HP to all allies at the start of each wave."},{"op":"replace","path":"/cards/1521/abilities/0/tags/1","value":"Team"},{"op":"replace","path":"/cards/1521/abilities/0/tags/2","value":"Heal"},{"op":"remove","path":"/cards/1521/abilities/1"},{"op":"replace","path":"/cards/1521/stats/max_hp","value":9300},{"op":"replace","path":"/cards/1521/stats/max_atk","value":13400},{"op":"replace","path":"/cards/1521/stats/base_atk","value":4465},{"op":"replace","path":"/cards/1521/stats/base_hp","value":3100},{"op":"replace","path":"/cards/1521/skill/prob_lb0","value":null},{"op":"move","from":"/cards/1521/skill/tags/1","path":"/cards/1521/abilities/0/tags/2"},{"op":"add","path":"/cards/1521/skill/tags/1","value":"Multi"},{"op":"replace","path":"/cards/1521/skill/tags/2","value":"DMG Up"},{"op":"remove","path":"/cards/1521/skill/tags/3"},{"op":"replace","path":"/cards/1521/skill/slv_mlb","value":"3,194"},{"op":"replace","path":"/cards/1521/skill/delay_mlb","value":"39.48%"},{"op":"replace","path":"/cards/1521/skill/delay_lb0","value":"33.08%"},{"op":"replace","path":"/cards/1521/skill/slv_lb0","value":"2,674"},{"op":"replace","path":"/cards/1521/skill/description","value":"Deals {value} DMG to the 2 enemies with the highest ATK, target receives {delay1} more DMG for a limited time."},{"op":"replace","path":"/cards/1521/skill/prob_mlb","value":null},{"op":"add","path":"/cards/1521/acquisition/sources/0","value":"exchange"},{"op":"replace","path":"/cards/1617/acquisition/has_tower_drops","value":true},{"op":"add","path":"/cards/1617/acquisition/sources/0","value":"event"},{"op":"replace","path":"/version","value":"9b3b2c7"},{"op":"replace","path":"/total_cards","value":952},{"op":"replace","path":"/data_hash","value":"30c5d887"}],"stats":{"total_operations":48,"add_operations":22,"remove_operations":2,"replace_operations":23,"move_operations":1,"copy_operations":0,"test_operations":0}}